openapi_toolkit/__init__.py
openapi_toolkit/cli.py
openapi_toolkit/openapi.py
openapi_toolkit/preprocessor.py
openapi_toolkit/resolver.py
openapi_toolkit/yaml.py
openapi_toolkit/schemas/3.0.json
openapi_toolkit/schemas/__init__.py
openapi_toolkit/validators/__init__.py
openapi_toolkit/validators/formats.py
openapi_toolkit-0.1.2.dist-info/LICENSE
openapi_toolkit-0.1.2.dist-info/METADATA
openapi_toolkit-0.1.2.dist-info/NOTICE
openapi_toolkit-0.1.2.dist-info/WHEEL
openapi_toolkit-0.1.2.dist-info/entry_points.txt
openapi_toolkit-0.1.2.dist-info/top_level.txt
openapi_toolkit-0.1.2.dist-info/RECORD
