Metadata-Version: 2.1
Name: openapi-toolkit
Version: 0.1.2
Summary: Collection of utilities for OpenAPIs
Home-page: https://github.com/jmvrbanac/openapi-toolkit
Author: John Vrbanac
Author-email: john.vrbanac@linux.com
License: Apache v2
Keywords: openapi toolkit resolver validator
Platform: UNKNOWN
Classifier: Development Status :: 3 - Alpha
Classifier: Intended Audience :: Developers
Classifier: License :: OSI Approved :: Apache Software License
Classifier: Programming Language :: Python :: 3.5
Classifier: Programming Language :: Python :: 3.6
Classifier: Programming Language :: Python :: 3.7
Requires-Dist: alchemize
Requires-Dist: jsonschema[format]
Requires-Dist: mako
Requires-Dist: ruamel.yaml
